mycalc/calculator.py
minhyeok112-1.0.post1.dist-info/METADATA
minhyeok112-1.0.post1.dist-info/WHEEL
minhyeok112-1.0.post1.dist-info/top_level.txt
minhyeok112-1.0.post1.dist-info/RECORD
