Metadata-Version: 2.1
Name: minhyeok112
Version: 1.0.post1
Summary: nice calc
Home-page: https://github.com/Kminhyeok/calc
Download-URL: https://github.com/Kminhyeok/calc
Author: minhhyeok
License: UNKNOWN
Platform: UNKNOWN
